setup.py
django_mercanet/__init__.py
django_mercanet/autoresponse.py
django_mercanet/request.py
django_mercanet/response.py
django_mercanet.egg-info/PKG-INFO
django_mercanet.egg-info/SOURCES.txt
django_mercanet.egg-info/dependency_links.txt
django_mercanet.egg-info/not-zip-safe
django_mercanet.egg-info/top_level.txt