Metadata-Version: 1.0
Name: django-mercanet
Version: 0.1
Summary: mercanet payment
Home-page: http://github.com/benjaminboumendil/django_mercanet
Author: Boumendil Benjamin
Author-email: bboumend@student.42.fr
License: UNKNOWN
Platform: UNKNOWN
